perf_end_Julespyvar/__init__.py
perf_end_Julespyvar/perf_end.py
perf_end_Julespyvar/endurance/__init__.py
perf_end_Julespyvar/endurance/imputer_endurance.joblib
perf_end_Julespyvar/endurance/model_description_endurance.txt
perf_end_Julespyvar/endurance/model_weights_endurance.ckpt.data-00000-of-00001
perf_end_Julespyvar/endurance/model_weights_endurance.ckpt.index
perf_end_Julespyvar/endurance/scaler_endurance.joblib
perf_end_Julespyvar/endurance/shap_values_endurance.joblib
perf_end_Julespyvar/performance/__init__.py
perf_end_Julespyvar/performance/imputer_performance.joblib
perf_end_Julespyvar/performance/model_description_performance.txt
perf_end_Julespyvar/performance/model_weights_performance.ckpt.data-00000-of-00001
perf_end_Julespyvar/performance/model_weights_performance.ckpt.index
perf_end_Julespyvar/performance/scaler_performance.joblib
perf_end_Julespyvar/performance/shap_valuesperformance.joblib
perf_end_Julespyvar-0.0.1.dist-info/LICENSE
perf_end_Julespyvar-0.0.1.dist-info/METADATA
perf_end_Julespyvar-0.0.1.dist-info/WHEEL
perf_end_Julespyvar-0.0.1.dist-info/top_level.txt
perf_end_Julespyvar-0.0.1.dist-info/RECORD
